diffport/__init__.py
diffport/cli.py
diffport/connection.py
diffport/core.py
diffport/exceptions.py
diffport/store.py
diffport/templates.py
diffport/watchers.py
diffport-0.2.1.dist-info/DESCRIPTION.rst
diffport-0.2.1.dist-info/METADATA
diffport-0.2.1.dist-info/RECORD
diffport-0.2.1.dist-info/WHEEL
diffport-0.2.1.dist-info/entry_points.txt
diffport-0.2.1.dist-info/metadata.json
diffport-0.2.1.dist-info/top_level.txt
tests/__init__.py
tests/test_core.py
tests/test_store_dir.py
tests/test_watchers.py
