Metadata-Version: 2.0
Name: diffport
Version: 0.2.1
Summary: Database summary diff reporting tool
Home-page: https://github.com/reichlab/diffport
Author: Abhinav Tushar
Author-email: abhinav.tushar.vs@gmail.com
License: UNKNOWN
Platform: UNKNOWN
Classifier: License :: OSI Approved :: GNU General Public License v3 (GPLv3)
Classifier: Natural Language :: English
Classifier: Programming Language :: Python
Classifier: Programming Language :: Python :: 3 :: Only
Requires-Dist: colorama
Requires-Dist: dataset
Requires-Dist: docopt
Requires-Dist: jinja2
Requires-Dist: psycopg2
Requires-Dist: pyyaml
Requires-Dist: tabulate
